project/__init__.py
project/requirements.txt
project/test_print.py
shuirouyan_package_test-0.0.3.dist-info/METADATA
shuirouyan_package_test-0.0.3.dist-info/WHEEL
shuirouyan_package_test-0.0.3.dist-info/entry_points.txt
shuirouyan_package_test-0.0.3.dist-info/top_level.txt
shuirouyan_package_test-0.0.3.dist-info/RECORD
