Metadata-Version: 2.1
Name: shuirouyan-package-test
Version: 0.0.3
Summary: pythonpypi update version
Author: shuirouyan
Author-email: ck163114@163.com
License: MIT
Requires-Python: >=3.6
Requires-Dist: annotated-types==0.7.0
Requires-Dist: anyio==4.6.2.post1
Requires-Dist: asttokens==3.0.0
Requires-Dist: attrs==24.2.0
Requires-Dist: Automat==24.8.1
Requires-Dist: backports.tarfile==1.2.0
Requires-Dist: beautifulsoup4==4.12.3
Requires-Dist: better-exceptions==0.3.3
Requires-Dist: blinker==1.9.0
Requires-Dist: Brotli==1.1.0
Requires-Dist: bs4==0.0.2
Requires-Dist: certifi==2024.8.30
Requires-Dist: cffi==1.17.1
Requires-Dist: charset-normalizer==3.4.0
Requires-Dist: cli-helpers==2.3.1
Requires-Dist: click==8.1.7
Requires-Dist: colorama==0.4.6
Requires-Dist: colored==1.4.4
Requires-Dist: configobj==5.0.9
Requires-Dist: constantly==23.10.4
Requires-Dist: contourpy==1.3.1
Requires-Dist: cryptography==44.0.0
Requires-Dist: cssselect==1.2.0
Requires-Dist: curl-cffi==0.10.0
Requires-Dist: cycler==0.12.1
Requires-Dist: DBUtils==3.1.0
Requires-Dist: decorator==5.1.1
Requires-Dist: defusedxml==0.7.1
Requires-Dist: delegator.py==0.1.1
Requires-Dist: distlib==0.3.9
Requires-Dist: distro==1.9.0
Requires-Dist: docutils==0.21.2
Requires-Dist: executing==2.1.0
Requires-Dist: Faker==36.1.1
Requires-Dist: fastapi==0.115.5
Requires-Dist: feapder==1.9.1
Requires-Dist: filelock==3.16.1
Requires-Dist: Flask==3.1.0
Requires-Dist: fonttools==4.55.3
Requires-Dist: frida==16.5.9
Requires-Dist: frida-tools==13.6.0
Requires-Dist: gevent==24.11.1
Requires-Dist: greenlet==3.1.1
Requires-Dist: h11==0.14.0
Requires-Dist: hexdump==3.3
Requires-Dist: httpcore==1.0.7
Requires-Dist: httpx==0.28.1
Requires-Dist: hyperlink==21.0.0
Requires-Dist: id==1.5.0
Requires-Dist: idna==3.10
Requires-Dist: importlib-metadata==8.7.0
Requires-Dist: incremental==24.7.2
Requires-Dist: influxdb==5.3.2
Requires-Dist: ipython==8.30.0
Requires-Dist: itemadapter==0.10.0
Requires-Dist: itemloaders==1.3.2
Requires-Dist: itsdangerous==2.2.0
Requires-Dist: jaraco.classes==3.4.0
Requires-Dist: jaraco.context==6.0.1
Requires-Dist: jaraco.functools==4.1.0
Requires-Dist: jedi==0.19.2
Requires-Dist: jieba==0.42.1
Requires-Dist: Jinja2==3.1.4
Requires-Dist: jiter==0.8.2
Requires-Dist: jmespath==1.0.1
Requires-Dist: keyring==25.6.0
Requires-Dist: kiwisolver==1.4.7
Requires-Dist: litecli==1.13.2
Requires-Dist: loguru==0.7.2
Requires-Dist: lxml==5.3.0
Requires-Dist: markdown-it-py==3.0.0
Requires-Dist: MarkupSafe==3.0.2
Requires-Dist: matplotlib==3.9.4
Requires-Dist: matplotlib-inline==0.1.7
Requires-Dist: mdurl==0.1.2
Requires-Dist: more-itertools==10.7.0
Requires-Dist: msgpack==1.1.0
Requires-Dist: nh3==0.2.21
Requires-Dist: numpy==2.2.0
Requires-Dist: objection==1.11.0
Requires-Dist: openai==1.65.3
Requires-Dist: opencv-python==4.11.0.86
Requires-Dist: packaging==24.2
Requires-Dist: parsel==1.9.1
Requires-Dist: parso==0.8.4
Requires-Dist: pexpect==4.9.0
Requires-Dist: pika==1.3.2
Requires-Dist: pika-stubs==0.1.3
Requires-Dist: pillow==11.0.0
Requires-Dist: platformdirs==4.3.7
Requires-Dist: prompt-toolkit==3.0.48
Requires-Dist: Protego==0.3.1
Requires-Dist: ptyprocess==0.7.0
Requires-Dist: pure-eval==0.2.3
Requires-Dist: pyasn1==0.6.1
Requires-Dist: pyasn1-modules==0.4.1
Requires-Dist: pycparser==2.22
Requires-Dist: pycryptodome==3.21.0
Requires-Dist: pydantic==2.10.2
Requires-Dist: pydantic-core==2.27.1
Requires-Dist: PyDispatcher==2.0.7
Requires-Dist: Pygments==2.18.0
Requires-Dist: PyMySQL==1.1.1
Requires-Dist: pyOpenSSL==24.3.0
Requires-Dist: pyparsing==3.2.0
Requires-Dist: pyperclip==1.9.0
Requires-Dist: pytesseract==0.3.13
Requires-Dist: python-dateutil==2.9.0.post0
Requires-Dist: python-dotenv==1.0.1
Requires-Dist: pytz==2024.2
Requires-Dist: pywin32-ctypes==0.2.3
Requires-Dist: queuelib==1.7.0
Requires-Dist: readme-renderer==44.0
Requires-Dist: redis==3.5.3
Requires-Dist: requests==2.32.3
Requires-Dist: requests-file==2.1.0
Requires-Dist: requests-toolbelt==1.0.0
Requires-Dist: rfc3986==2.0.0
Requires-Dist: rich==14.0.0
Requires-Dist: Scrapy==2.12.0
Requires-Dist: semver==2.13.0
Requires-Dist: service-identity==24.2.0
Requires-Dist: six==1.17.0
Requires-Dist: sniffio==1.3.1
Requires-Dist: socksio==1.0.0
Requires-Dist: some-package==0.1
Requires-Dist: soupsieve==2.6
Requires-Dist: sqlparse==0.5.3
Requires-Dist: stack-data==0.6.3
Requires-Dist: starlette==0.41.3
Requires-Dist: tabulate==0.9.0
Requires-Dist: terminal-layout==3.0.0
Requires-Dist: tldextract==5.1.3
Requires-Dist: tqdm==4.67.1
Requires-Dist: traitlets==5.14.3
Requires-Dist: twine==6.1.0
Requires-Dist: Twisted==24.11.0
Requires-Dist: typing-extensions==4.12.2
Requires-Dist: tzdata==2025.1
Requires-Dist: urllib3==2.2.3
Requires-Dist: uvicorn==0.32.1
Requires-Dist: w3lib==2.2.1
Requires-Dist: wcwidth==0.2.13
Requires-Dist: websocket==0.2.1
Requires-Dist: websocket-client==1.8.0
Requires-Dist: websockets==13.1
Requires-Dist: Werkzeug==3.1.3
Requires-Dist: win32-setctime==1.1.0
Requires-Dist: wordcloud==1.9.4
Requires-Dist: zipp==3.21.0
Requires-Dist: zope.event==5.0
Requires-Dist: zope.interface==7.2
